coocan/__init__.py
coocan/gen.py
coocan/p2.py
coocan/_examples/crawl_csdn_detail.py
coocan/_examples/crawl_csdn_list.py
coocan/_examples/recv_item.py
coocan/_examples/use_proxy.py
coocan/_examples/view_local_ip.py
coocan/cmd/__init__.py
coocan/cmd/cli.py
coocan/spider/__init__.py
coocan/spider/base.py
coocan/templates/spider.txt
coocan/url/__init__.py
coocan/url/errs.py
coocan/url/request.py
coocan/url/response.py
coocan-0.6.2.dist-info/METADATA
coocan-0.6.2.dist-info/WHEEL
coocan-0.6.2.dist-info/entry_points.txt
coocan-0.6.2.dist-info/top_level.txt
coocan-0.6.2.dist-info/RECORD
