Metadata-Version: 2.4
Name: coocan
Version: 0.6.2
Summary: Air Async Spider Framework
Author-email: wauo <markadc@126.com>
License-Expression: MIT
Project-URL: Homepage, https://github.com/markadc/coocan
Requires-Python: >=3.10
Requires-Dist: click>=8.0.0
Requires-Dist: httpx
Requires-Dist: loguru
Requires-Dist: parsel
